CO221-labs/Lab8/behaviour level/Dflipflop.v
module test;

    reg CLK,D,RST;
    wire Q;
    
    dff flipflop(D, CLK, RST, Q);

    // Testing field
    initial begin
        CLK=1;
        D=0;
        RST=1;
        
        $dumpfile("D.vcd");
        $dumpvars(0, flipflop);
        
        #1 D = 1;
        #3 RST = 0;
        #8 D = 0;
        #6 D = 1;
        #2 D = 0;
        #6 D = 1;
        #5 D = 0;
        #6 D = 1;
        #10 RST = 1;
        #10 $finish;
    
    end

always #5 CLK = ~CLK;
   
endmodule


module dff (d ,clk, reset, q);

input clk, reset, d;
output q;
reg q;
  	  	 
always @ (posedge clk or posedge reset)
begin
  if (reset == 1)
     q <= 0;
 else 
     q <= d;
 end
  	  	 
endmodule

CO221-labs/Lab8/behaviour level/D.vcd
$date
	Thu May 17 14:23:04 2018
$end
$version
	Icarus Verilog
$end
$timescale
	1s
$end
$scope module test $end
$scope module flipflop $end
$var wire 1 ! clk $end
$var wire 1 " d $end
$var wire 1 # reset $end
$var reg 1 $ q $end
$upscope $end
$upscope $end
$enddefinitions $end
#0
$dumpvars
0$
1#
0"
1!
$end
#1
1"
#4
0#
#5
0!
#10
1$
1!
#12
0"
#15
0!
#18
1"
#20
0$
0"
1!
#25
0!
#26
1"
#30
1$
1!
#31
0"
#35
0!
#37
1"
#40
1!
#45
0!
#47
0$
1#
