CO221-labs/Lab7/4bitRippleAdder/ripAdd4.v
/**************************************************************
	Lab 7: 4bit Ripple Full Adder

	Author: Jaliyagoda A.J.N.M. (E/15/140)
	Last Update: 2018/05/26

**************************************************************/

module testbench;

	reg [3:0] A,B;
	wire [3:0] S;
	wire cOut;
	reg [3:0] i,j;
	
	bitFullAdder myFullAdder(A,B,S, 1'b0, cOut);
	
	initial begin
		A <= 4'b0000;
		B <= 4'b0000;

		$dumpfile("adder.vcd"); 
		$dumpvars(0, myFullAdder);
     
 
		for(i=0; i<15; i=i+1) begin
			#1 $display(" A(0000),  B(0000),  S(0000), cOut\n");

			for(j=0; j<15; j=j+1) begin
				A <= i;
 				B <= j;
				#2 $display("%2d(%b), %2d(%b), %2d(%b), %b", i, i, j, j, S, S, cOut);
	  		end
			#1 $display("\n");
  		end
		
		#10 $finish;
	end

endmodule

module bitFullAdder(A,B,S,cIn,cOut);

	//get A,B (4bit registers), cIn and results R(4bit), cOut

	input [3:0] A,B;
	input cIn;

	output [3:0] S;
	output cOut;

	wire w1, w2, w3;
 
	fullAdder add1(A[0], B[0], cIn, w1, S[0]);
	fullAdder add2(A[1], B[1], w1, w2, S[1]);
	fullAdder add3(A[2], B[2], w2, w3, S[2]);
	fullAdder add4(A[3], B[3], w3, cOut, S[3]);

endmodule

module fullAdder(A, B, cIn, cOut, S);

	input A,B, cIn;
	output cOut, S;
	wire x,y,z, p;

	halfAdder add1(A,B, x, y);
	halfAdder add2(y, cIn, z, S);
	or u1(cOut, x, z);
	
	/*input A,B,cIn; output S,cOut;
	assign {cOut,S} = A + B + cIn;
	*/
endmodule

module halfAdder(A, B, cOut, S);
	// Get A,B bits and results A+B

	input A,B;
	output cOut, S;

	and u1(cOut, A,B);
	xor u2(S, A,B);

endmodule

CO221-labs/Lab7/4bitRippleAdder/adder.vcd
$date
	Sat May 26 12:08:44 2018
$end
$version
	Icarus Verilog
$end
$timescale
	1s
$end
$scope module testbench $end
$scope module myFullAdder $end
$var wire 4 ! A [3:0] $end
$var wire 4 " B [3:0] $end
$var wire 4 # S [3:0] $end
$var wire 1 $ cIn $end
$var wire 1 % cOut $end
$var wire 1 & w1 $end
$var wire 1 ' w2 $end
$var wire 1 ( w3 $end
$scope module add1 $end
$var wire 1 ) A $end
$var wire 1 * B $end
$var wire 1 + S $end
$var wire 1 $ cIn $end
$var wire 1 & cOut $end
$var wire 1 , x $end
$var wire 1 - y $end
$var wire 1 . z $end
$scope module add1 $end
$var wire 1 ) A $end
$var wire 1 * B $end
$var wire 1 - S $end
$var wire 1 , cOut $end
$upscope $end
$scope module add2 $end
$var wire 1 - A $end
$var wire 1 $ B $end
$var wire 1 + S $end
$var wire 1 . cOut $end
$upscope $end
$upscope $end
$scope module add2 $end
$var wire 1 / A $end
$var wire 1 0 B $end
$var wire 1 1 S $end
$var wire 1 & cIn $end
$var wire 1 ' cOut $end
$var wire 1 2 x $end
$var wire 1 3 y $end
$var wire 1 4 z $end
$scope module add1 $end
$var wire 1 / A $end
$var wire 1 0 B $end
$var wire 1 3 S $end
$var wire 1 2 cOut $end
$upscope $end
$scope module add2 $end
$var wire 1 3 A $end
$var wire 1 & B $end
$var wire 1 1 S $end
$var wire 1 4 cOut $end
$upscope $end
$upscope $end
$scope module add3 $end
$var wire 1 5 A $end
$var wire 1 6 B $end
$var wire 1 7 S $end
$var wire 1 ' cIn $end
$var wire 1 ( cOut $end
$var wire 1 8 x $end
$var wire 1 9 y $end
$var wire 1 : z $end
$scope module add1 $end
$var wire 1 5 A $end
$var wire 1 6 B $end
$var wire 1 9 S $end
$var wire 1 8 cOut $end
$upscope $end
$scope module add2 $end
$var wire 1 9 A $end
$var wire 1 ' B $end
$var wire 1 7 S $end
$var wire 1 : cOut $end
$upscope $end
$upscope $end
$scope module add4 $end
$var wire 1 ; A $end
$var wire 1 < B $end
$var wire 1 = S $end
$var wire 1 ( cIn $end
$var wire 1 % cOut $end
$var wire 1 > x $end
$var wire 1 ? y $end
$var wire 1 @ z $end
$scope module add1 $end
$var wire 1 ; A $end
$var wire 1 < B $end
$var wire 1 ? S $end
$var wire 1 > cOut $end
$upscope $end
$scope module add2 $end
$var wire 1 ? A $end
$var wire 1 ( B $end
$var wire 1 = S $end
$var wire 1 @ cOut $end
$upscope $end
$upscope $end
$upscope $end
$upscope $end
$enddefinitions $end
#0
$dumpvars
0@
0?
0>
0=
0<
0;
0:
09
08
07
06
05
04
03
02
01
00
0/
0.
0-
0,
0+
0*
0)
0(
0'
0&
0%
0$
b0 #
b0 "
b0 !
$end
#3
1+
b1 #
1-
1*
b1 "
#5
0+
11
b10 #
0-
13
0*
10
b10 "
#7
1+
b11 #
1-
1*
b11 "
#9
0+
01
17
b100 #
0-
03
19
0*
00
16
b100 "
#11
1+
b101 #
1-
1*
b101 "
#13
0+
11
b110 #
0-
13
0*
10
b110 "
#15
1+
b111 #
1-
1*
b111 "
#17
0+
01
07
1=
b1000 #
0-
03
09
1?
0*
00
06
1<
b1000 "
#19
1+
b1001 #
1-
1*
b1001 "
#21
0+
11
b1010 #
0-
13
0*
10
b1010 "
#23
1+
b1011 #
1-
1*
b1011 "
#25
0+
01
17
b1100 #
0-
03
19
0*
00
16
b1100 "
#27
1+
b1101 #
1-
1*
b1101 "
#29
0+
11
b1110 #
0-
13
0*
10
b1110 "
#33
01
07
0=
1+
b1 #
03
09
0?
1-
00
06
0<
1)
b0 "
b1 !
#35
11
1&
0+
b10 #
1,
0-
1*
b1 "
#37
07
0'
0&
1+
04
11
b11 #
0,
1-
13
0*
10
b10 "
#39
17
1'
14
01
1&
0+
b100 #
1,
0-
1*
b11 "
#41
0=
0'
0(
0&
1+
04
01
0:
17
b101 #
0,
1-
03
19
0*
00
16
b100 "
#43
11
1&
0+
b110 #
1,
0-
1*
b101 "
#45
0=
0(
0:
17
0'
0&
1+
04
11
b111 #
0,
1-
13
0*
10
b110 "
#47
1=
1(
1:
07
1'
14
01
1&
0+
b1000 #
1,
0-
1*
b111 "
#49
0'
0(
0%
0&
1+
04
01
0:
07
0@
1=
b1001 #
0,
1-
03
09
1?
0*
00
06
1<
b1000 "
#51
11
1&
0+
b1010 #
1,
0-
1*
b1001 "
#53
07
0'
0&
1+
04
11
b1011 #
0,
1-
13
0*
10
b1010 "
#55
17
1'
14
01
1&
0+
b1100 #
1,
0-
1*
b1011 "
#57
0%
0@
1=
0'
0(
0&
1+
04
01
0:
17
b1101 #
0,
1-
03
19
0*
00
16
b1100 "
#59
11
1&
0+
b1110 #
1,
0-
1*
b1101 "
#61
0%
0@
1=
0(
0:
17
0'
0&
1+
04
11
b1111 #
0,
1-
13
0*
10
b1110 "
#65
07
0=
0+
b10 #
09
0?
0-
00
06
0<
0)
1/
b0 "
b10 !
#67
1+
b11 #
1-
1*
b1 "
#69
17
0+
1'
01
b100 #
0-
12
03
0*
10
b10 "
#71
1+
b101 #
1-
1*
b11 "
#73
0=
0(
0+
0'
11
0:
17
b110 #
0-
02
13
19
0*
00
16
b100 "
#75
1+
b111 #
1-
1*
b101 "
#77
1=
1(
1:
07
0+
1'
01
b1000 #
0-
12
03
0*
10
b110 "
#79
1+
b1001 #
1-
1*
b111 "
#81
0(
0%
0+
0'
11
0:
07
0@
1=
b1010 #
0-
02
13
09
1?
0*
00
06
1<
b1000 "
#83
1+
b1011 #
1-
1*
b1001 "
#85
17
0+
1'
01
b1100 #
0-
12
03
0*
10
b1010 "
#87
1+
b1101 #
1-
1*
b1011 "
#89
0%
0@
1=
0(
0+
0'
11
0:
17
b1110 #
0-
02
13
19
0*
00
16
b1100 "
#91
1+
b1111 #
1-
1*
b1101 "
#93
1%
1@
0=
1(
1:
07
0+
1'
01
b0 #
0-
12
03
0*
10
b1110 "
#97
0(
0%
0'
11
0:
07
0@
0=
1+
b11 #
02
13
09
0?
1-
00
06
0<
1)
b0 "
b11 !
#99
17
1'
14
01
1&
0+
b100 #
1,
0-
1*
b1 "
#101
0&
1+
04
01
b101 #
0,
1-
12
03
0*
10
b10 "
#103
11
1&
0+
b110 #
1,
0-
1*
b11 "
#105
0'
0=
0(
0&
1+
04
11
0:
17
b111 #
0,
1-
02
13
19
0*
00
16
b100 "
#107
1=
1(
1:
07
1'
14
01
1&
0+
b1000 #
1,
0-
1*
b101 "
#109
0&
1+
04
01
b1001 #
0,
1-
12
03
0*
10
b110 "
#111
11
1&
0+
b1010 #
1,
0-
1*
b111 "
#113
0'
0(
0%
0&
1+
04
11
0:
07
0@
1=
b1011 #
0,
1-
02
13
09
1?
0*
00
06
1<
b1000 "
#115
17
1'
14
01
1&
0+
b1100 #
1,
0-
1*
b1001 "
#117
0&
1+
04
01
b1101 #
0,
1-
12
03
0*
10
b1010 "
#119
11
1&
0+
b1110 #
1,
0-
1*
b1011 "
#121
0%
0'
0@
1=
0(
0&
1+
04
11
0:
17
b1111 #
0,
1-
02
13
19
0*
00
16
b1100 "
#123
1%
1@
0=
1(
1:
07
1'
14
01
1&
0+
b0 #
1,
0-
1*
b1101 "
#125
0&
1+
04
01
b1 #
0,
1-
12
03
0*
10
b1110 "
#129
0(
0%
0:
17
0@
0=
0+
b100 #
0'
0?
0-
02
00
06
0<
0)
0/
15
b0 "
b100 !
#131
1+
b101 #
1-
1*
b1 "
#133
0+
11
b110 #
0-
13
0*
10
b10 "
#135
1+
b111 #
1-
1*
b11 "
#137
1=
0+
01
1(
07
b1000 #
0-
03
18
09
0*
00
16
b100 "
#139
1+
b1001 #
1-
1*
b101 "
#141
0+
11
b1010 #
0-
13
0*
10
b110 "
#143
1+
b1011 #
1-
1*
b111 "
#145
0%
0+
01
0(
17
0@
1=
b1100 #
0-
03
08
19
1?
0*
00
06
1<
b1000 "
#147
1+
b1101 #
1-
1*
b1001 "
#149
0+
11
b1110 #
0-
13
0*
10
b1010 "
#151
1+
b1111 #
1-
1*
b1011 "
#153
1%
1@
0=
0+
01
1(
07
b0 #
0-
03
18
09
0*
00
16
b1100 "
#155
1+
b1 #
1-
1*
b1101 "
#157
0+
11
b10 #
0-
13
0*
10
b1110 "
#161
0%
01
0(
17
0@
0=
1+
b101 #
03
08
19
0?
1-
00
06
0<
1)
b0 "
b101 !
#163
11
1&
0+
b110 #
1,
0-
1*
b1 "
#165
0=
0(
0:
17
0'
0&
1+
04
11
b111 #
0,
1-
13
0*
10
b10 "
#167
1=
1(
1:
07
1'
14
01
1&
0+
b1000 #
1,
0-
1*
b11 "
#169
0'
0&
1+
04
01
0:
07
b1001 #
0,
1-
03
18
09
0*
00
16
b100 "
#171
11
1&
0+
b1010 #
1,
0-
1*
b101 "
#173
07
0'
0&
1+
04
11
b1011 #
0,
1-
13
0*
10
b110 "
#175
17
1'
14
01
1&
0+
b1100 #
1,
0-
1*
b111 "
#177
0(
0'
0%
0&
1+
04
01
0:
17
0@
1=
b1101 #
0,
1-
03
08
19
1?
0*
00
06
1<
b1000 "
#179
11
1&
0+
b1110 #
1,
0-
1*
b1001 "
#181
0%
0@
1=
0(
0:
17
0'
0&
1+
04
11
b1111 #
0,
1-
13
0*
10
b1010 "
#183
1%
1@
0=
1(
1:
07
1'
14
01
1&
0+
b0 #
1,
0-
1*
b1011 "
#185
0'
0&
1+
04
01
0:
07
b1 #
0,
1-
03
18
09
0*
00
16
b1100 "
#187
11
1&
0+
b10 #
1,
0-
1*
b1101 "
#189
07
0'
0&
1+
04
11
b11 #
0,
1-
13
0*
10
b1110 "
#193
0%
0(
17
0@
0=
0+
b110 #
08
19
0?
0-
00
06
0<
0)
1/
b0 "
b110 !
#195
1+
b111 #
1-
1*
b1 "
#197
1=
1(
1:
07
0+
1'
01
b1000 #
0-
12
03
0*
10
b10 "
#199
1+
b1001 #
1-
1*
b11 "
#201
0+
0'
11
0:
07
b1010 #
0-
02
13
18
09
0*
00
16
b100 "
#203
1+
b1011 #
1-
1*
b101 "
#205
17
0+
1'
01
b1100 #
0-
12
03
0*
10
b110 "
#207
1+
b1101 #
1-
1*
b111 "
#209
0(
0%
0+
0'
11
0:
17
0@
1=
b1110 #
0-
02
13
08
19
1?
0*
00
06
1<
b1000 "
#211
1+
b1111 #
1-
1*
b1001 "
#213
1%
1@
0=
1(
1:
07
0+
1'
01
b0 #
0-
12
03
0*
10
b1010 "
#215
1+
b1 #
1-
1*
b1011 "
#217
0+
0'
11
0:
07
b10 #
0-
02
13
18
09
0*
00
16
b1100 "
#219
1+
b11 #
1-
1*
b1101 "
#221
17
0+
1'
01
b100 #
0-
12
03
0*
10
b1110 "
#225
0(
0%
0'
11
0:
17
0@
0=
1+
b111 #
02
13
08
19
0?
1-
00
06
0<
1)
b0 "
b111 !
#227
1=
1(
1:
07
1'
14
01
1&
0+
b1000 #
1,
0-
1*
b1 "
#229
0&
1+
04
01
b1001 #
0,
1-
12
03
0*
10
b10 "
#231
11
1&
0+
b1010 #
1,
0-
1*
b11 "
#233
0'
0&
1+
04
11
0:
07
b1011 #
0,
1-
02
13
18
09
0*
00
16
b100 "
#235
17
1'
14
01
1&
0+
b1100 #
1,
0-
1*
b101 "
#237
0&
1+
04
01
b1101 #
0,
1-
12
03
0*
10
b110 "
#239
11
1&
0+
b1110 #
1,
0-
1*
b111 "
#241
0(
0'
0%
0&
1+
04
11
0:
17
0@
1=
b1111 #
0,
1-
02
13
08
19
1?
0*
00
06
1<
b1000 "
#243
1%
1@
0=
1(
1:
07
1'
14
01
1&
0+
b0 #
1,
0-
1*
b1001 "
#245
0&
1+
04
01
b1 #
0,
1-
12
03
0*
10
b1010 "
#247
11
1&
0+
b10 #
1,
0-
1*
b1011 "
#249
0'
0&
1+
04
11
0:
07
b11 #
0,
1-
02
13
18
09
0*
00
16
b1100 "
#251
17
1'
14
01
1&
0+
b100 #
1,
0-
1*
b1101 "
#253
0&
1+
04
01
b101 #
0,
1-
12
03
0*
10
b1110 "
#257
0%
07
0@
1=
0+
b1000 #
0'
0(
0-
02
08
00
06
0<
0)
0/
05
1;
b0 "
b1000 !
#259
1+
b1001 #
1-
1*
b1 "
#261
0+
11
b1010 #
0-
13
0*
10
b10 "
#263
1+
b1011 #
1-
1*
b11 "
#265
0+
01
17
b1100 #
0-
03
19
0*
00
16
b100 "
#267
1+
b1101 #
1-
1*
b101 "
#269
0+
11
b1110 #
0-
13
0*
10
b110 "
#271
1+
b1111 #
1-
1*
b111 "
#273
0+
01
07
1%
0=
b0 #
0-
03
09
1>
0?
0*
00
06
1<
b1000 "
#275
1+
b1 #
1-
1*
b1001 "
#277
0+
11
b10 #
0-
13
0*
10
b1010 "
#279
1+
b11 #
1-
1*
b1011 "
#281
0+
01
17
b100 #
0-
03
19
0*
00
16
b1100 "
#283
1+
b101 #
1-
1*
b1101 "
#285
0+
11
b110 #
0-
13
0*
10
b1110 "
#289
01
07
0%
1=
1+
b1001 #
03
09
0>
1?
1-
00
06
0<
1)
b0 "
b1001 !
#291
11
1&
0+
b1010 #
1,
0-
1*
b1 "
#293
07
0'
0&
1+
04
11
b1011 #
0,
1-
13
0*
10
b10 "
#295
17
1'
14
01
1&
0+
b1100 #
1,
0-
1*
b11 "
#297
0%
0@
1=
0'
0(
0&
1+
04
01
0:
17
b1101 #
0,
1-
03
19
0*
00
16
b100 "
#299
11
1&
0+
b1110 #
1,
0-
1*
b101 "
#301
0%
0@
1=
0(
0:
17
0'
0&
1+
04
11
b1111 #
0,
1-
13
0*
10
b110 "
#303
1%
1@
0=
1(
1:
07
1'
14
01
1&
0+
b0 #
1,
0-
1*
b111 "
#305
0'
0(
0&
1+
04
01
0:
07
0@
0=
b1 #
0,
1-
03
09
1>
0?
0*
00
06
1<
b1000 "
#307
11
1&
0+
b10 #
1,
0-
1*
b1001 "
#309
07
0'
0&
1+
04
11
b11 #
0,
1-
13
0*
10
b1010 "
#311
17
1'
14
01
1&
0+
b100 #
1,
0-
1*
b1011 "
#313
0=
0'
0(
0&
1+
04
01
0:
17
b101 #
0,
1-
03
19
0*
00
16
b1100 "
#315
11
1&
0+
b110 #
1,
0-
1*
b1101 "
#317
0=
0(
0:
17
0'
0&
1+
04
11
b111 #
0,
1-
13
0*
10
b1110 "
#321
07
0%
1=
0+
b1010 #
09
0>
1?
0-
00
06
0<
0)
1/
b0 "
b1010 !
#323
1+
b1011 #
1-
1*
b1 "
#325
17
0+
1'
01
b1100 #
0-
12
03
0*
10
b10 "
#327
1+
b1101 #
1-
1*
b11 "
#329
0%
0@
1=
0(
0+
0'
11
0:
17
b1110 #
0-
02
13
19
0*
00
16
b100 "
#331
1+
b1111 #
1-
1*
b101 "
#333
1%
1@
0=
1(
1:
07
0+
1'
01
b0 #
0-
12
03
0*
10
b110 "
#335
1+
b1 #
1-
1*
b111 "
#337
0(
0+
0'
11
0:
07
0@
0=
b10 #
0-
02
13
09
1>
0?
0*
00
06
1<
b1000 "
#339
1+
b11 #
1-
1*
b1001 "
#341
17
0+
1'
01
b100 #
0-
12
03
0*
10
b1010 "
#343
1+
b101 #
1-
1*
b1011 "
#345
0=
0(
0+
0'
11
0:
17
b110 #
0-
02
13
19
0*
00
16
b1100 "
#347
1+
b111 #
1-
1*
b1101 "
#349
1=
1(
1:
07
0+
1'
01
b1000 #
0-
12
03
0*
10
b1110 "
#353
0%
0(
0'
11
0:
07
0@
1=
1+
b1011 #
02
13
09
0>
1?
1-
00
06
0<
1)
b0 "
b1011 !
#355
17
1'
14
01
1&
0+
b1100 #
1,
0-
1*
b1 "
#357
0&
1+
04
01
b1101 #
0,
1-
12
03
0*
10
b10 "
#359
11
1&
0+
b1110 #
1,
0-
1*
b11 "
#361
0%
0'
0@
1=
0(
0&
1+
04
11
0:
17
b1111 #
0,
1-
02
13
19
0*
00
16
b100 "
#363
1%
1@
0=
1(
1:
07
1'
14
01
1&
0+
b0 #
1,
0-
1*
b101 "
#365
0&
1+
04
01
b1 #
0,
1-
12
03
0*
10
b110 "
#367
11
1&
0+
b10 #
1,
0-
1*
b111 "
#369
0'
0(
0&
1+
04
11
0:
07
0@
0=
b11 #
0,
1-
02
13
09
1>
0?
0*
00
06
1<
b1000 "
#371
17
1'
14
01
1&
0+
b100 #
1,
0-
1*
b1001 "
#373
0&
1+
04
01
b101 #
0,
1-
12
03
0*
10
b1010 "
#375
11
1&
0+
b110 #
1,
0-
1*
b1011 "
#377
0'
0=
0(
0&
1+
04
11
0:
17
b111 #
0,
1-
02
13
19
0*
00
16
b1100 "
#379
1=
1(
1:
07
1'
14
01
1&
0+
b1000 #
1,
0-
1*
b1101 "
#381
0&
1+
04
01
b1001 #
0,
1-
12
03
0*
10
b1110 "
#385
0%
0(
0:
17
0@
1=
0+
b1100 #
0'
0>
1?
0-
02
00
06
0<
0)
0/
15
b0 "
b1100 !
#387
1+
b1101 #
1-
1*
b1 "
#389
0+
11
b1110 #
0-
13
0*
10
b10 "
#391
1+
b1111 #
1-
1*
b11 "
#393
1%
1@
0=
0+
01
1(
07
b0 #
0-
03
18
09
0*
00
16
b100 "
#395
1+
b1 #
1-
1*
b101 "
#397
0+
11
b10 #
0-
13
0*
10
b110 "
#399
1+
b11 #
1-
1*
b111 "
#401
0+
01
0(
17
0@
0=
b100 #
0-
03
08
19
1>
0?
0*
00
06
1<
b1000 "
#403
1+
b101 #
1-
1*
b1001 "
#405
0+
11
b110 #
0-
13
0*
10
b1010 "
#407
1+
b111 #
1-
1*
b1011 "
#409
1=
0+
01
1(
07
b1000 #
0-
03
18
09
0*
00
16
b1100 "
#411
1+
b1001 #
1-
1*
b1101 "
#413
0+
11
b1010 #
0-
13
0*
10
b1110 "
#417
0%
01
0(
17
0@
1=
1+
b1101 #
03
08
19
0>
1?
1-
00
06
0<
1)
b0 "
b1101 !
#419
11
1&
0+
b1110 #
1,
0-
1*
b1 "
#421
0%
0@
1=
0(
0:
17
0'
0&
1+
04
11
b1111 #
0,
1-
13
0*
10
b10 "
#423
1%
1@
0=
1(
1:
07
1'
14
01
1&
0+
b0 #
1,
0-
1*
b11 "
#425
0'
0&
1+
04
01
0:
07
b1 #
0,
1-
03
18
09
0*
00
16
b100 "
#427
11
1&
0+
b10 #
1,
0-
1*
b101 "
#429
07
0'
0&
1+
04
11
b11 #
0,
1-
13
0*
10
b110 "
#431
17
1'
14
01
1&
0+
b100 #
1,
0-
1*
b111 "
#433
0(
0'
0&
1+
04
01
0:
17
0@
0=
b101 #
0,
1-
03
08
19
1>
0?
0*
00
06
1<
b1000 "
#435
11
1&
0+
b110 #
1,
0-
1*
b1001 "
#437
0=
0(
0:
17
0'
0&
1+
04
11
b111 #
0,
1-
13
0*
10
b1010 "
#439
1=
1(
1:
07
1'
14
01
1&
0+
b1000 #
1,
0-
1*
b1011 "
#441
0'
0&
1+
04
01
0:
07
b1001 #
0,
1-
03
18
09
0*
00
16
b1100 "
#443
11
1&
0+
b1010 #
1,
0-
1*
b1101 "
#445
07
0'
0&
1+
04
11
b1011 #
0,
1-
13
0*
10
b1110 "
#449
0%
0(
17
0@
1=
0+
b1110 #
08
19
0>
1?
0-
00
06
0<
0)
1/
b0 "
b1110 !
#451
1+
b1111 #
1-
1*
b1 "
#453
1%
1@
0=
1(
1:
07
0+
1'
01
b0 #
0-
12
03
0*
10
b10 "
#455
1+
b1 #
1-
1*
b11 "
#457
0+
0'
11
0:
07
b10 #
0-
02
13
18
09
0*
00
16
b100 "
#459
1+
b11 #
1-
1*
b101 "
#461
17
0+
1'
01
b100 #
0-
12
03
0*
10
b110 "
#463
1+
b101 #
1-
1*
b111 "
#465
0(
0+
0'
11
0:
17
0@
0=
b110 #
0-
02
13
08
19
1>
0?
0*
00
06
1<
b1000 "
#467
1+
b111 #
1-
1*
b1001 "
#469
1=
1(
1:
07
0+
1'
01
b1000 #
0-
12
03
0*
10
b1010 "
#471
1+
b1001 #
1-
1*
b1011 "
#473
0+
0'
11
0:
07
b1010 #
0-
02
13
18
09
0*
00
16
b1100 "
#475
1+
b1011 #
1-
1*
b1101 "
#477
17
0+
1'
01
b1100 #
0-
12
03
0*
10
b1110 "
